{"nodes": [{"id": "externaldns_values_cloudflare", "label": "ExternalDNS Cloudflare Provider Config", "file_type": "code", "source_file": "infrastructure/controllers/base/external-dns/values.yaml", "source_location": "provider.name=cloudflare", "source_url": null, "captured_at": null, "author": null, "contributor": null}, {"id": "externaldns_values_cfsecret", "label": "Cloudflare API Key Secret Reference", "file_type": "concept", "source_file": "infrastructure/controllers/base/external-dns/values.yaml", "source_location": "env[0].valueFrom.secretKeyRef.name=cloudflare-api-key", "source_url": null, "captured_at": null, "author": null, "contributor": null}], "edges": [{"source": "externaldns_values_cloudflare", "target": "externaldns_values_cfsecret", "relation": "references", "confidence": "EXTRACTED", "confidence_score": 1.0, "source_file": "infrastructure/controllers/base/external-dns/values.yaml", "source_location": "env[0].valueFrom.secretKeyRef.name=cloudflare-api-key", "weight": 1.0}], "hyperedges": []}